diffipy/Node.py
diffipy/NodesDifferentiation.py
diffipy/NodesLinearAlgebra.py
diffipy/NodesOperations.py
diffipy/NodesVariables.py
diffipy/__init__.py
diffipy/backend_config.py
diffipy/diffipy.py
diffipy/backends/BackendHelper.py
diffipy/backends/__init__.py
diffipy/backends/aadc/NodesAadc.py
diffipy/backends/aadc/__init__.py
diffipy/backends/aadc/aadc_config.py
diffipy/backends/jax/NodesJax.py
diffipy/backends/jax/__init__.py
diffipy/backends/jax/jax_config.py
diffipy/backends/numpy/NodesNumpy.py
diffipy/backends/numpy/__init__.py
diffipy/backends/numpy/numpy_config.py
diffipy/backends/pytorch/NodesPytorch.py
diffipy/backends/pytorch/__init__.py
diffipy/backends/pytorch/pytorch_config.py
diffipy/backends/tensorflow/NodesTensorflow.py
diffipy/backends/tensorflow/__init__.py
diffipy/backends/tensorflow/tensorflow_config.py
diffipy-0.0.10.dist-info/METADATA
diffipy-0.0.10.dist-info/WHEEL
diffipy-0.0.10.dist-info/top_level.txt
diffipy-0.0.10.dist-info/RECORD
