Metadata-Version: 2.1
Name: diffipy
Version: 0.0.10
Summary: An interface to differentiation backends in Python..
Home-page: https://github.com/da-roth/DiffiPy/src/
Author: Daniel Roth
Author-email: danielroth@posteo.eu
Classifier: Programming Language :: Python :: 3
Classifier: License :: OSI Approved :: MIT License
Classifier: Operating System :: OS Independent
Requires-Python: >=3.6
Requires-Dist: numpy
